setup.py
gauss_bi_dist/Binomialdistribution.py
gauss_bi_dist/Gaussiandistribution.py
gauss_bi_dist/Generaldistribution.py
gauss_bi_dist/__init__.py
gauss_bi_dist.egg-info/PKG-INFO
gauss_bi_dist.egg-info/SOURCES.txt
gauss_bi_dist.egg-info/dependency_links.txt
gauss_bi_dist.egg-info/not-zip-safe
gauss_bi_dist.egg-info/top_level.txt