Metadata-Version: 1.0
Name: gauss-bi-dist
Version: 1.0
Summary: Gaussian and Binomial distributions
Home-page: UNKNOWN
Author: Syed Suhail Salaha
Author-email: syedsuhailslh@gmail.com
License: UNKNOWN
Platform: UNKNOWN
